example.py
multiplereturn.py
multiplereturntest.py
MultipleReturn-0.1.0a1.dist-info/DESCRIPTION.rst
MultipleReturn-0.1.0a1.dist-info/METADATA
MultipleReturn-0.1.0a1.dist-info/metadata.json
MultipleReturn-0.1.0a1.dist-info/RECORD
MultipleReturn-0.1.0a1.dist-info/top_level.txt
MultipleReturn-0.1.0a1.dist-info/WHEEL
