Metadata-Version: 2.0
Name: MultipleReturn
Version: 0.1.0a1
Summary: An implementation of multiple return values.
Home-page: https://github.com/Gregory-Bell/MultipleReturn`
Author: Gregory Bell
Author-email: gregoryscottbell@gmail.com
License: GPLv3+
Keywords: multiple return values decorator
Platform: UNKNOWN
Classifier: License :: OSI Approved :: GNU General Public License v3 or later (GPLv3+)
Classifier: Development Status :: 3 - Alpha
Classifier: Programming Language :: Python :: 3
Classifier: Intended Audience :: Developers
Classifier: Topic :: Software Development :: Libraries :: Python Modules
